colorpaws/__init__.py
colorpaws-25.3.1.dist-info/LICENSE
colorpaws-25.3.1.dist-info/METADATA
colorpaws-25.3.1.dist-info/WHEEL
colorpaws-25.3.1.dist-info/top_level.txt
colorpaws-25.3.1.dist-info/RECORD
