Metadata-Version: 2.2
Name: colorpaws
Version: 25.3.1
Summary: A logging component with colored output and automated file organization.
Author-email: ikmalsaid <ikmalsaid@gmail.com>
Project-URL: Homepage, https://github.com/ikmalsaid/colorpaws
Project-URL: Issues, https://github.com/ikmalsaid/colorpaws/issues
Classifier: Programming Language :: Python :: 3
Classifier: License :: OSI Approved :: MIT License
Classifier: Operating System :: OS Independent
Classifier: Topic :: System :: Logging
Requires-Python: >=3.8
License-File: LICENSE
Requires-Dist: colorama
